dagger/__init__.py
dagger/_engine/_version.py
dagger/_exceptions.py
dagger/_managers.py
dagger/client/__init__.py
dagger/client/_config.py
dagger/client/_connection.py
dagger/client/_core.py
dagger/client/_guards.py
dagger/client/_session.py
dagger/client/base.py
dagger/client/gen.py
dagger/log.py
dagger/mod/__init__.py
dagger/mod/_arguments.py
dagger/mod/_converter.py
dagger/mod/_exceptions.py
dagger/mod/_module.py
dagger/mod/_resolver.py
dagger/mod/_types.py
dagger/mod/_utils.py
dagger/mod/cli.py
dagger/provisioning/__init__.py
dagger/provisioning/_config.py
dagger/provisioning/_connection.py
dagger/provisioning/_download.py
dagger/provisioning/_engine.py
dagger/provisioning/_exceptions.py
dagger/provisioning/_progress.py
dagger/provisioning/_session.py
dagger/py.typed
dagger/telemetry.py
dagger_io-0.19.9.dist-info/WHEEL
dagger_io-0.19.9.dist-info/METADATA
dagger_io-0.19.9.dist-info/RECORD
